tests/__init__.py
tests/test_shortener.py
uuid_shortener/__init__.py
uuid_shortener/shortener.py
uuid_shortener_py-0.0.2.dist-info/METADATA
uuid_shortener_py-0.0.2.dist-info/RECORD
uuid_shortener_py-0.0.2.dist-info/WHEEL
uuid_shortener_py-0.0.2.dist-info/top_level.txt
