Metadata-Version: 2.1
Name: uuid-shortener-py
Version: 0.0.2
Summary: Shorten a uuid into a URL friendly format.
Home-page: https://github.com/El-Sam/uuid_shortener
Author: Samira El Aabidi
Author-email: sam.elaabidi@gmail.com
License: UNKNOWN
Keywords: Python,UUID,UUID Shortener,Hex base,Short URL
Platform: UNKNOWN
Classifier: Programming Language :: Python :: 3.5
Classifier: Programming Language :: Python :: 3.6
Classifier: Development Status :: 5 - Production/Stable
Classifier: Intended Audience :: Developers
Classifier: Intended Audience :: Information Technology
Classifier: License :: OSI Approved :: MIT License
Classifier: Natural Language :: English
Classifier: Operating System :: OS Independent
Classifier: Topic :: Software Development :: Libraries :: Python Modules
Requires-Dist: pybaseconv (==0.*)
